xtract_sdk/__init__.py
xtract_sdk/xtract.py
xtract_sdk/agent/__init__.py
xtract_sdk/agent/xtract.py
xtract_sdk/client/__init__.py
xtract_sdk/client/xtract_client.py
xtract_sdk/decompressor/__init__.py
xtract_sdk/decompressor/decompressor.py
xtract_sdk/downloaders/__init__.py
xtract_sdk/downloaders/base.py
xtract_sdk/downloaders/figshare.py
xtract_sdk/downloaders/globus_https.py
xtract_sdk/downloaders/globus_tc.py
xtract_sdk/downloaders/google_drive.py
xtract_sdk/downloaders/local.py
xtract_sdk/downloaders/tests/__init__.py
xtract_sdk/downloaders/tests/globus_https_test.py
xtract_sdk/downloaders/tests/test_families.py
xtract_sdk/downloaders/tests/test_figshare.py
xtract_sdk/downloaders/tests/test_google_drive.py
xtract_sdk/downloaders/tests/xtract_agent_test.py
xtract_sdk/packagers/__init__.py
xtract_sdk/packagers/family.py
xtract_sdk/packagers/family_batch.py
xtract_sdk/packagers/group.py
xtract_sdk/utils/__init__.py
xtract_sdk/utils/xtract_utils.py
xtract_sdk-0.0.6.dist-info/LICENSE
xtract_sdk-0.0.6.dist-info/METADATA
xtract_sdk-0.0.6.dist-info/WHEEL
xtract_sdk-0.0.6.dist-info/top_level.txt
xtract_sdk-0.0.6.dist-info/RECORD
